{
  "$schema": "https://mintlify.com/docs.json",
  "name": "PIXA Wallet Docs",
  "theme": "mint",
  "colors": {
    "primary": "#0FB98A",
    "light": "#68F0CC",
    "dark": "#0B5D4B"
  },
  "favicon": "/favicon.svg",
  "navigation": {
    "tabs": [
      {
        "tab": "Overview",
        "groups": [
          {
            "group": "Introduction",
            "pages": [
              "index",
              "overview/about",
              "overview/use-cases",
              "overview/token-economics"
            ]
          },
          {
            "group": "Architecture",
            "pages": [
              "overview/architecture",
              "overview/components"
            ]
          }
        ]
      },
      {
        "tab": "Getting Started",
        "groups": [
          {
            "group": "Install PIXA",
            "pages": [
              "guides/quickstart",
              "guides/installation"
            ]
          },
          {
            "group": "Quality",
            "pages": [
              "guides/testing",
              "guides/contributing",
              "development"
            ]
          }
        ]
      },
      {
        "tab": "Tool Reference",
        "groups": [
          {
            "group": "Wallet and Payments",
            "pages": [
              "api-reference/introduction",
              "api-reference/user-management",
              "api-reference/referral-operations",
              "api-reference/badge-reputation"
            ]
          },
          {
            "group": "Funding and Routing",
            "pages": [
              "api-reference/nft-operations",
              "api-reference/quest-system",
              "api-reference/seasonal-competitions",
              "api-reference/partner-integration"
            ]
          },
          {
            "group": "Operations and Types",
            "pages": [
              "api-reference/leaderboard",
              "api-reference/utility-functions",
              "api-reference/typescript-types"
            ]
          }
        ]
      }
    ],
    "global": {
      "anchors": [
        {
          "anchor": "GitHub",
          "href": "https://github.com/soumyacodes007/algorand-wallet",
          "icon": "github"
        },
        {
          "anchor": "npm",
          "href": "https://www.npmjs.com/package/pixa-wallet-mcp",
          "icon": "package"
        }
      ]
    }
  },
  "logo": {
    "light": "/logo/light.svg",
    "dark": "/logo/dark.svg"
  },
  "navbar": {
    "links": [
      {
        "label": "npm package",
        "href": "https://www.npmjs.com/package/pixa-wallet-mcp"
      }
    ],
    "primary": {
      "type": "button",
      "label": "Quickstart",
      "href": "/guides/quickstart"
    }
  },
  "contextual": {
    "options": [
      "copy",
      "view"
    ]
  },
  "footer": {
    "socials": {
      "github": "https://github.com/soumyacodes007/algorand-wallet"
    }
  }
}
